Metadata-Version: 2.1
Name: extraterrestrial-life-equations
Version: 0.1
Summary: Extraterrestrial life calculations
Home-page: UNKNOWN
Author: José Manuel Villalba Jiménez
Author-email: josevillalbajimenez@gmail.com
License: UNKNOWN
Platform: UNKNOWN
